satplan/__init__.py
satplan/cli/__init__.py
satplan/cli/generate.py
satplan/cli/main.py
satplan-0.0.1.dist-info/METADATA
satplan-0.0.1.dist-info/WHEEL
satplan-0.0.1.dist-info/entry_points.txt
satplan-0.0.1.dist-info/top_level.txt
satplan-0.0.1.dist-info/RECORD
