Metadata-Version: 2.4
Name: satplan
Version: 0.0.1
Summary: SATPLAN is a package for training, benchmarking, and reference implementations for satellite task planning.
Author-email: Duncan Eddy <deddy@stanford.edu>
Requires-Python: >=3.11
Requires-Dist: typer>=0.16.0
